topical_matcher/__init__.py
topical_matcher-0.0.1.dist-info/licenses/LICENSE
topical_matcher-0.0.1.dist-info/METADATA
topical_matcher-0.0.1.dist-info/WHEEL
topical_matcher-0.0.1.dist-info/top_level.txt
topical_matcher-0.0.1.dist-info/RECORD
