Metadata-Version: 2.4
Name: topical-matcher
Version: 0.0.1
Summary: UDC/IAB document classification toolkit (coming soon)
Author: Turov Team
License-Expression: LicenseRef-Dual-License
Project-URL: Homepage, https://github.com/turov/topical-matcher
Keywords: classification,udc,iab,taxonomy,nlp
Classifier: Development Status :: 1 - Planning
Classifier: Intended Audience :: Developers
Classifier: Programming Language :: Python :: 3
Classifier: Programming Language :: Python :: 3.10
Classifier: Programming Language :: Python :: 3.11
Classifier: Programming Language :: Python :: 3.12
Requires-Python: >=3.10
License-File: LICENSE
Dynamic: license-file
